multineat-0.12.dist-info/LICENSE
multineat-0.12.dist-info/top_level.txt
multineat-0.12.dist-info/WHEEL
multineat-0.12.dist-info/RECORD
multineat-0.12.dist-info/METADATA
multineat/viz.py
multineat/__init__.py
multineat/_multineat.cpython-312-x86_64-linux-gnu.so
