Metadata-Version: 2.1
Name: multineat
Version: 0.12
Home-page: https://github.com/ci-group/MultiNEAT
License-File: LICENSE
